<?xml version="1.0" encoding="utf-8"?>
<doctrine-mapping xmlns="http://doctrine-project.org/schemas/orm/doctrine-mapping" xmlns:xsi="http://www.w3.org/2001/XMLSchema-instance" xsi:schemaLocation="http://doctrine-project.org/schemas/orm/doctrine-mapping http://doctrine-project.org/schemas/orm/doctrine-mapping.xsd">
  <entity name="AppBundle\Entity\Medicament" table="medicament">
    <indexes>
      <index name="fk_pharmacien" columns="usrRole"/>
    </indexes>
    <id name="idMedicament" type="integer" column="id_medicament">
      <generator strategy="IDENTITY"/>
    </id>
    <field name="nomMedicament" type="string" column="nom_medicament" length="50" nullable="false">
      <options>
        <option name="fixed"/>
      </options>
    </field>
    <field name="prix" type="float" column="prix" precision="10" scale="0" nullable="false"/>
    <field name="nomLabo" type="string" column="nom_labo" length="50" nullable="false">
      <options>
        <option name="fixed"/>
      </options>
    </field>
    <field name="usrrole" type="string" column="usrRole" length="12" nullable="false">
      <options>
        <option name="fixed"/>
      </options>
    </field>
  </entity>
</doctrine-mapping>
